Metadata-Version: 1.1
Name: pylocated
Version: 2.0.1
Summary: python interface for locate command
Home-page: https://github.com/plasmashadow/pylocated.git
Author: plasmashadow
Author-email: plasmashadowx@gmail.com
License: MIT
Platform: UNKNOWN
Classifier: Programming Language :: Python
Classifier: License :: OSI Approved :: GNU General Public License (GPL)
